kiwoomapi/__init__.py
kiwoomapi/api.py
kiwoomapi/const.py
kiwoomapi/core.py
kiwoomapi/mdb.py
kiwoomapi/metadata/ErrorCode.py
kiwoomapi/metadata/__init__.py
kiwoomapi-0.5.4.dist-info/LICENSE
kiwoomapi-0.5.4.dist-info/METADATA
kiwoomapi-0.5.4.dist-info/WHEEL
kiwoomapi-0.5.4.dist-info/top_level.txt
kiwoomapi-0.5.4.dist-info/RECORD
