Metadata-Version: 2.1
Name: kiwoomapi
Version: 0.5.4
Summary: Windows COM 기반으로 파이썬 32비트로만 동작하는 키움증권 오픈API 패키지
Home-page: https://github.com/innovata/KiwoomOpenAPI
Author: innovata sambong
Author-email: iinnovata@gmail.com
Classifier: Programming Language :: Python :: 3
Classifier: License :: OSI Approved :: MIT License
Classifier: Operating System :: OS Independent
Requires-Python: >=3.8
License-File: LICENSE
Requires-Dist: PyQt5 ==5.15.1
Requires-Dist: ipylib
